ytdlp_plugins/extractor/bittube.py
ytdlp_bittube-2022.1.2.dist-info/LICENSE
ytdlp_bittube-2022.1.2.dist-info/METADATA
ytdlp_bittube-2022.1.2.dist-info/WHEEL
ytdlp_bittube-2022.1.2.dist-info/top_level.txt
ytdlp_bittube-2022.1.2.dist-info/RECORD
