Metadata-Version: 2.1
Name: ytdlp-bittube
Version: 2022.1.2
Summary: yt-dlp extractor for bittube.tv
Home-page: https://github.com/flashdagger/ytdlp-plugins/tree/bittube
Author: flashdagger
Author-email: flashdagger@googlemail.com
License: The Unlicense
Keywords: yt-dlp,youtube-dl,bittube,extractors,plugins
Platform: any
Classifier: Development Status :: 4 - Beta
Classifier: License :: OSI Approved :: The Unlicense (Unlicense)
Classifier: Programming Language :: Python :: 3
Classifier: Programming Language :: Python :: 3.6
Classifier: Programming Language :: Python :: 3.7
Classifier: Programming Language :: Python :: 3.8
Classifier: Programming Language :: Python :: 3.9
Classifier: Programming Language :: Python :: 3.10
Classifier: Programming Language :: Python :: Implementation
Classifier: Programming Language :: Python :: Implementation :: CPython
Classifier: Programming Language :: Python :: Implementation :: PyPy
Classifier: Operating System :: OS Independent
Classifier: Environment :: Console
Classifier: Environment :: Plugins
Classifier: Topic :: Multimedia :: Video
Requires-Python: >=3.6
Requires-Dist: ytdlp-plugins (>=2021.11.17)
